{"info": {"gameMode": "normal", "name": "New Ball Help Test2", "author": "Anonymous"}, "portals": {"10,23": {"cooldown": 0, "destination": {"y": 5, "x": 11}}, "19,5": {"cooldown": 0, "destination": {"y": 23, "x": 20}}, "20,23": {"cooldown": 0, "destination": {"y": 5, "x": 19}}, "11,5": {"cooldown": 0, "destination": {"y": 23, "x": 10}}}, "fields": {"10,22": {"defaultState": "blue"}, "9,23": {"defaultState": "blue"}, "21,23": {"defaultState": "red"}, "20,22": {"defaultState": "red"}}, "switches": {}, "marsballs": [], "spawnPoints": {"blue": [], "red": []}}