{"info": {"name": "Easter Map from memory", "author": "Ball-E"}, "switches": {}, "portals": {"12,12": {"destination": {"y": 6, "x": 25}}, "38,38": {"destination": {"y": 44, "x": 25}}, "44,44": {"cooldown": 0, "destination": {"y": 38, "x": 38}}, "6,44": {"cooldown": 0, "destination": {"y": 38, "x": 12}}, "12,38": {"destination": {"y": 44, "x": 25}}, "44,6": {"cooldown": 0, "destination": {"y": 12, "x": 38}}, "38,12": {"destination": {"y": 6, "x": 25}}, "6,6": {"cooldown": 2, "destination": {"y": 12, "x": 12}}}, "fields": {}}