{"info": {"gameMode": "normal", "name": "Nosferatu", "author": "Moosen"}, "portals": {"13,11": {"cooldown": 0, "destination": {"y": 15, "x": 13}}, "13,12": {"cooldown": 0, "destination": {"y": 15, "x": 13}}, "45,12": {"cooldown": 0, "destination": {"y": 15, "x": 45}}, "53,12": {"cooldown": 0, "destination": {"y": 12, "x": 13}}, "5,11": {"cooldown": 0, "destination": {"y": 11, "x": 45}}, "5,12": {"cooldown": 0, "destination": {"y": 12, "x": 45}}, "53,11": {"cooldown": 0, "destination": {"y": 11, "x": 13}}, "45,11": {"cooldown": 0, "destination": {"y": 15, "x": 45}}}, "fields": {"6,11": {"defaultState": "blue"}, "34,10": {"defaultState": "blue"}, "34,12": {"defaultState": "blue"}, "6,12": {"defaultState": "blue"}, "24,10": {"defaultState": "red"}, "52,11": {"defaultState": "red"}, "24,12": {"defaultState": "red"}, "52,12": {"defaultState": "red"}}, "switches": {"36,11": {"toggle": [{"pos": {"y": 10, "x": 34}}, {"pos": {"y": 12, "x": 34}}], "timer": 0}, "26,11": {"toggle": [{"pos": {"y": 10, "x": 24}}, {"pos": {"y": 12, "x": 24}}], "timer": 0}, "32,11": {"toggle": [{"pos": {"y": 10, "x": 34}}, {"pos": {"y": 12, "x": 34}}], "timer": 0}, "22,11": {"toggle": [{"pos": {"y": 10, "x": 24}}, {"pos": {"y": 12, "x": 24}}], "timer": 0}}, "marsballs": [], "spawnPoints": {"blue": [{"y": 9, "x": 47, "radius": 2, "weight": 1}, {"y": 14, "x": 47, "radius": 2, "weight": 1}], "red": [{"y": 9, "x": 11, "radius": 2, "weight": 1}, {"y": 14, "x": 11, "radius": 2, "weight": 1}]}}