{"info": {"gameMode": "normal", "name": "Untitled V", "author": "Omnivore"}, "portals": {}, "fields": {"9,20": {"defaultState": "off"}, "10,20": {"defaultState": "off"}, "10,21": {"defaultState": "off"}, "8,19": {"defaultState": "off"}, "31,6": {"defaultState": "off"}, "31,7": {"defaultState": "off"}, "11,21": {"defaultState": "off"}, "9,19": {"defaultState": "off"}, "29,5": {"defaultState": "off"}, "11,22": {"defaultState": "off"}, "30,5": {"defaultState": "off"}, "30,6": {"defaultState": "off"}, "32,7": {"defaultState": "off"}, "29,4": {"defaultState": "off"}}, "switches": {"9,23": {"toggle": [], "timer": 0}, "31,3": {"toggle": [], "timer": 0}}, "marsballs": [], "spawnPoints": {"blue": [], "red": []}}