{"info": {"gameMode": "normal", "name": "Chase", "author": "Barry"}, "portals": {}, "fields": {"10,31": {"defaultState": "off"}, "31,9": {"defaultState": "off"}, "33,9": {"defaultState": "off"}, "6,9": {"defaultState": "off"}, "7,9": {"defaultState": "off"}, "11,9": {"defaultState": "off"}, "9,9": {"defaultState": "off"}, "10,9": {"defaultState": "off"}, "8,9": {"defaultState": "off"}, "6,31": {"defaultState": "off"}, "29,31": {"defaultState": "off"}, "9,31": {"defaultState": "off"}, "8,31": {"defaultState": "off"}, "7,31": {"defaultState": "off"}, "30,31": {"defaultState": "off"}, "31,31": {"defaultState": "off"}, "29,9": {"defaultState": "off"}, "34,31": {"defaultState": "off"}, "32,31": {"defaultState": "off"}, "11,31": {"defaultState": "off"}, "30,9": {"defaultState": "off"}, "32,9": {"defaultState": "off"}, "33,31": {"defaultState": "off"}, "34,9": {"defaultState": "off"}}, "switches": {"20,14": {"toggle": [{"pos": {"y": 31, "x": 34}}, {"pos": {"y": 9, "x": 34}}, {"pos": {"y": 31, "x": 33}}, {"pos": {"y": 9, "x": 33}}, {"pos": {"y": 31, "x": 32}}, {"pos": {"y": 9, "x": 32}}, {"pos": {"y": 31, "x": 31}}, {"pos": {"y": 9, "x": 31}}, {"pos": {"y": 31, "x": 30}}, {"pos": {"y": 9, "x": 30}}, {"pos": {"y": 31, "x": 29}}, {"pos": {"y": 9, "x": 29}}, {"pos": {"y": 23, "x": 20}}, {"pos": {"y": 31, "x": 11}}, {"pos": {"y": 9, "x": 11}}, {"pos": {"y": 31, "x": 10}}, {"pos": {"y": 9, "x": 10}}, {"pos": {"y": 31, "x": 9}}, {"pos": {"y": 9, "x": 9}}, {"pos": {"y": 31, "x": 8}}, {"pos": {"y": 9, "x": 8}}, {"pos": {"y": 31, "x": 7}}, {"pos": {"y": 9, "x": 7}}, {"pos": {"y": 31, "x": 6}}, {"pos": {"y": 9, "x": 6}}], "timer": 0}, "20,26": {"toggle": [{"pos": {"y": 9, "x": 6}}, {"pos": {"y": 31, "x": 6}}, {"pos": {"y": 9, "x": 7}}, {"pos": {"y": 31, "x": 7}}, {"pos": {"y": 9, "x": 8}}, {"pos": {"y": 31, "x": 8}}, {"pos": {"y": 9, "x": 9}}, {"pos": {"y": 31, "x": 9}}, {"pos": {"y": 9, "x": 10}}, {"pos": {"y": 31, "x": 10}}, {"pos": {"y": 9, "x": 11}}, {"pos": {"y": 31, "x": 11}}, {"pos": {"y": 17, "x": 20}}, {"pos": {"y": 9, "x": 29}}, {"pos": {"y": 31, "x": 29}}, {"pos": {"y": 9, "x": 30}}, {"pos": {"y": 31, "x": 30}}, {"pos": {"y": 9, "x": 31}}, {"pos": {"y": 31, "x": 31}}, {"pos": {"y": 9, "x": 32}}, {"pos": {"y": 31, "x": 32}}, {"pos": {"y": 9, "x": 33}}, {"pos": {"y": 31, "x": 33}}, {"pos": {"y": 9, "x": 34}}, {"pos": {"y": 31, "x": 34}}], "timer": 0}}, "marsballs": [], "spawnPoints": {"blue": [], "red": []}}