{"info": {"gameMode": "normal", "name": "DIY axis", "author": "Ball-E"}, "portals": {}, "fields": {"36,12": {"defaultState": "off"}, "22,14": {"defaultState": "off"}, "19,14": {"defaultState": "off"}, "22,13": {"defaultState": "off"}, "34,13": {"defaultState": "off"}, "34,12": {"defaultState": "off"}, "36,11": {"defaultState": "off"}, "35,12": {"defaultState": "off"}, "33,12": {"defaultState": "off"}, "20,14": {"defaultState": "off"}, "20,15": {"defaultState": "off"}, "23,14": {"defaultState": "off"}, "37,12": {"defaultState": "off"}, "21,14": {"defaultState": "off"}}, "switches": {"21,13": {"toggle": [], "timer": 0}, "35,13": {"toggle": [], "timer": 0}, "21,15": {"toggle": [], "timer": 0}, "35,11": {"toggle": [], "timer": 0}}, "marsballs": [], "spawnPoints": {"blue": [], "red": []}}