{"info": {"gameMode": "normal", "name": "at least qlzfto likes my maps", "author": "velkin"}, "portals": {"33,21": {"cooldown": 20000, "destination": {"y": 14, "x": 32}}, "32,14": {}, "31,21": {"cooldown": 20000, "destination": {"y": 14, "x": 32}}}, "fields": {}, "switches": {"46,12": {"toggle": [{"pos": {"y": 7, "x": 40}}], "timer": 0}, "18,12": {"toggle": [{"pos": {"y": 7, "x": 24}}], "timer": 0}, "47,11": {"toggle": [{"pos": {"y": 7, "x": 41}}], "timer": 0}, "17,11": {"toggle": [{"pos": {"y": 7, "x": 23}}], "timer": 0}}, "marsballs": [], "spawnPoints": {"blue": [], "red": []}}