{"info": {"gameMode": "normal", "name": "Inquisitor", "author": "Antigod"}, "portals": {"2,54": {"cooldown": 10000, "destination": {"y": 55, "x": 7}}, "2,56": {}, "51,55": {}, "56,54": {"cooldown": 10000, "destination": {"y": 55, "x": 51}}, "3,51": {}, "56,56": {}, "30,48": {"cooldown": 10000, "destination": {"y": 56, "x": 56}}, "28,48": {"cooldown": 10000, "destination": {"y": 56, "x": 2}}, "29,43": {"cooldown": 10000, "destination": {"y": 50, "x": 29}}, "55,51": {}, "29,50": {}, "7,55": {}, "4,56": {"cooldown": 10000, "destination": {"y": 51, "x": 3}}, "54,56": {"cooldown": 10000, "destination": {"y": 51, "x": 55}}}, "fields": {"33,48": {"defaultState": "off"}, "25,48": {"defaultState": "off"}, "25,49": {"defaultState": "off"}, "33,51": {"defaultState": "off"}, "25,52": {"defaultState": "off"}, "25,51": {"defaultState": "off"}, "25,50": {"defaultState": "off"}, "33,50": {"defaultState": "off"}, "33,49": {"defaultState": "off"}, "33,52": {"defaultState": "off"}}, "switches": {"25,46": {"toggle": [{"pos": {"y": 48, "x": 25}}, {"pos": {"y": 49, "x": 25}}, {"pos": {"y": 50, "x": 25}}, {"pos": {"y": 51, "x": 25}}, {"pos": {"y": 52, "x": 25}}], "timer": 0}, "33,46": {"toggle": [{"pos": {"y": 48, "x": 33}}, {"pos": {"y": 49, "x": 33}}, {"pos": {"y": 50, "x": 33}}, {"pos": {"y": 51, "x": 33}}, {"pos": {"y": 52, "x": 33}}], "timer": 0}}, "marsballs": [], "spawnPoints": {"blue": [], "red": []}}