{"info": {"gameMode": "normal", "name": "Mild High Fix", "author": "Ken M."}, "portals": {}, "fields": {"29,26": {"defaultState": "blue"}, "29,27": {"defaultState": "blue"}, "19,7": {"defaultState": "red"}, "36,3": {"defaultState": "blue"}, "48,18": {"defaultState": "blue"}, "14,24": {"defaultState": "red"}, "38,5": {"defaultState": "blue"}, "38,4": {"defaultState": "blue"}, "22,14": {"defaultState": "on"}, "22,15": {"defaultState": "on"}, "17,27": {"defaultState": "red"}, "22,13": {"defaultState": "on"}, "37,24": {"defaultState": "blue"}, "44,23": {"defaultState": "blue"}, "11,6": {"defaultState": "red"}, "18,27": {"defaultState": "red"}, "41,6": {"defaultState": "blue"}, "10,20": {"defaultState": "on"}, "46,6": {"defaultState": "blue"}, "36,23": {"defaultState": "blue"}, "10,24": {"defaultState": "red"}, "40,6": {"defaultState": "blue"}, "21,28": {"defaultState": "on"}, "48,6": {"defaultState": "blue"}, "38,24": {"defaultState": "blue"}, "34,17": {"defaultState": "on"}, "33,17": {"defaultState": "on"}, "15,6": {"defaultState": "red"}, "22,28": {"defaultState": "on"}, "34,19": {"defaultState": "off"}, "34,18": {"defaultState": "off"}, "32,2": {"defaultState": "on"}, "30,2": {"defaultState": "on"}, "20,10": {"defaultState": "off"}, "20,11": {"defaultState": "off"}, "20,12": {"defaultState": "off"}, "20,13": {"defaultState": "on"}, "25,3": {"defaultState": "red"}, "25,4": {"defaultState": "red"}, "37,4": {"defaultState": "blue"}, "9,24": {"defaultState": "red"}, "10,19": {"defaultState": "on"}, "10,18": {"defaultState": "on"}, "25,28": {"defaultState": "on"}, "31,6": {"defaultState": "on"}, "39,5": {"defaultState": "blue"}, "39,6": {"defaultState": "blue"}, "21,13": {"defaultState": "on"}, "12,6": {"defaultState": "red"}, "6,15": {"defaultState": "red"}, "6,14": {"defaultState": "red"}, "6,17": {"defaultState": "red"}, "6,16": {"defaultState": "red"}, "6,11": {"defaultState": "red"}, "6,10": {"defaultState": "red"}, "6,13": {"defaultState": "red"}, "6,12": {"defaultState": "red"}, "32,23": {"defaultState": "blue"}, "6,19": {"defaultState": "red"}, "6,18": {"defaultState": "red"}, "32,24": {"defaultState": "blue"}, "48,19": {"defaultState": "blue"}, "48,7": {"defaultState": "blue"}, "8,9": {"defaultState": "red"}, "8,8": {"defaultState": "red"}, "21,7": {"defaultState": "red"}, "16,6": {"defaultState": "red"}, "42,10": {"defaultState": "on"}, "16,25": {"defaultState": "red"}, "16,26": {"defaultState": "red"}, "43,10": {"defaultState": "on"}, "32,17": {"defaultState": "on"}, "32,16": {"defaultState": "on"}, "32,15": {"defaultState": "on"}, "17,26": {"defaultState": "red"}, "48,20": {"defaultState": "blue"}, "43,6": {"defaultState": "blue"}, "47,20": {"defaultState": "blue"}, "24,4": {"defaultState": "red"}, "24,5": {"defaultState": "red"}, "13,24": {"defaultState": "red"}, "18,7": {"defaultState": "red"}, "18,6": {"defaultState": "red"}, "23,24": {"defaultState": "on"}, "15,25": {"defaultState": "red"}, "15,24": {"defaultState": "red"}, "7,24": {"defaultState": "red"}, "23,28": {"defaultState": "on"}, "43,24": {"defaultState": "blue"}, "44,12": {"defaultState": "on"}, "44,10": {"defaultState": "on"}, "44,11": {"defaultState": "on"}, "30,25": {"defaultState": "blue"}, "13,6": {"defaultState": "red"}, "31,25": {"defaultState": "blue"}, "31,24": {"defaultState": "blue"}, "37,3": {"defaultState": "blue"}, "20,8": {"defaultState": "off"}, "20,9": {"defaultState": "off"}, "35,23": {"defaultState": "blue"}, "20,7": {"defaultState": "red"}, "34,20": {"defaultState": "off"}, "34,21": {"defaultState": "off"}, "34,22": {"defaultState": "off"}, "34,23": {"defaultState": "blue"}, "19,28": {"defaultState": "on"}, "17,6": {"defaultState": "red"}, "47,6": {"defaultState": "blue"}, "45,6": {"defaultState": "blue"}, "31,2": {"defaultState": "on"}, "26,28": {"defaultState": "on"}, "42,6": {"defaultState": "blue"}, "8,10": {"defaultState": "red"}, "20,28": {"defaultState": "on"}, "7,10": {"defaultState": "red"}, "44,6": {"defaultState": "blue"}, "45,22": {"defaultState": "blue"}, "29,2": {"defaultState": "on"}, "27,2": {"defaultState": "on"}, "30,26": {"defaultState": "blue"}, "44,22": {"defaultState": "blue"}, "41,24": {"defaultState": "blue"}, "40,24": {"defaultState": "blue"}, "28,27": {"defaultState": "blue"}, "39,24": {"defaultState": "blue"}, "34,2": {"defaultState": "on"}, "23,5": {"defaultState": "red"}, "23,6": {"defaultState": "red"}, "48,8": {"defaultState": "blue"}, "48,9": {"defaultState": "blue"}, "33,2": {"defaultState": "on"}, "46,20": {"defaultState": "blue"}, "8,24": {"defaultState": "red"}, "36,24": {"defaultState": "blue"}, "35,2": {"defaultState": "on"}, "12,20": {"defaultState": "on"}, "12,24": {"defaultState": "red"}, "9,8": {"defaultState": "red"}, "11,20": {"defaultState": "on"}, "10,8": {"defaultState": "red"}, "11,24": {"defaultState": "red"}, "33,23": {"defaultState": "blue"}, "10,7": {"defaultState": "red"}, "10,6": {"defaultState": "red"}, "48,16": {"defaultState": "blue"}, "28,2": {"defaultState": "on"}, "48,17": {"defaultState": "blue"}, "48,14": {"defaultState": "blue"}, "46,21": {"defaultState": "blue"}, "26,3": {"defaultState": "red"}, "14,6": {"defaultState": "red"}, "48,12": {"defaultState": "blue"}, "44,24": {"defaultState": "blue"}, "48,13": {"defaultState": "blue"}, "27,28": {"defaultState": "on"}, "48,15": {"defaultState": "blue"}, "48,10": {"defaultState": "blue"}, "48,11": {"defaultState": "blue"}, "42,24": {"defaultState": "blue"}, "22,6": {"defaultState": "red"}, "22,7": {"defaultState": "red"}, "6,24": {"defaultState": "red"}, "24,28": {"defaultState": "on"}, "46,22": {"defaultState": "blue"}, "6,20": {"defaultState": "red"}, "6,21": {"defaultState": "red"}, "6,22": {"defaultState": "red"}, "6,23": {"defaultState": "red"}}, "switches": {"18,15": {"toggle": [{"pos": {"y": 8, "x": 20}}, {"pos": {"y": 9, "x": 20}}, {"pos": {"y": 10, "x": 20}}, {"pos": {"y": 11, "x": 20}}, {"pos": {"y": 12, "x": 20}}], "timer": 0}, "36,15": {"toggle": [{"pos": {"y": 22, "x": 34}}, {"pos": {"y": 21, "x": 34}}, {"pos": {"y": 20, "x": 34}}, {"pos": {"y": 19, "x": 34}}, {"pos": {"y": 18, "x": 34}}], "timer": 0}}, "marsballs": [], "spawnPoints": {"blue": [], "red": []}}