{"info": {"gameMode": "gravityCTF", "name": "How good are you?", "author": "9bob9"}, "portals": {"4,70": {"cooldown": 0, "destination": {"y": 60, "x": 7}}, "1,72": {"cooldown": 0, "destination": {"y": 60, "x": 7}}, "3,74": {"cooldown": 0, "destination": {"y": 60, "x": 7}}, "7,60": {}, "5,72": {"cooldown": 0, "destination": {"y": 60, "x": 7}}, "2,70": {"cooldown": 0, "destination": {"y": 60, "x": 7}}}, "fields": {"3,80": {"defaultState": "on"}, "8,38": {"defaultState": "on"}, "1,38": {"defaultState": "on"}, "6,74": {"defaultState": "on"}, "6,78": {"defaultState": "on"}, "4,80": {"defaultState": "on"}, "5,41": {"defaultState": "on"}, "2,80": {"defaultState": "on"}, "5,80": {"defaultState": "on"}, "4,41": {"defaultState": "on"}, "1,80": {"defaultState": "on"}}, "switches": {}, "marsballs": [{"y": 60, "x": 2}, {"y": 60, "x": 4}], "spawnPoints": {"blue": [], "red": [{"y": 1, "x": 2, "radius": 5, "weight": 1}, {"y": 1, "x": 7, "radius": 5, "weight": 1}]}}