{"info": {"gameMode": "normal", "name": "Norton Hears a Who", "author": "canvas probably"}, "portals": {"1,11": {"cooldown": 0, "destination": {"y": 8, "x": 6}}, "50,8": {"cooldown": 0, "destination": {"y": 8, "x": 50}}, "55,11": {"cooldown": 0, "destination": {"y": 8, "x": 50}}, "6,8": {"cooldown": 0, "destination": {"y": 8, "x": 6}}}, "fields": {"7,18": {"defaultState": "off"}, "8,18": {"defaultState": "off"}, "48,18": {"defaultState": "off"}, "47,17": {"defaultState": "off"}, "47,16": {"defaultState": "off"}, "49,18": {"defaultState": "off"}, "9,16": {"defaultState": "off"}, "9,17": {"defaultState": "off"}}, "switches": {"48,17": {"toggle": [{"pos": {"y": 16, "x": 47}}, {"pos": {"y": 17, "x": 47}}, {"pos": {"y": 18, "x": 48}}, {"pos": {"y": 18, "x": 49}}], "timer": 0}, "8,17": {"toggle": [{"pos": {"y": 18, "x": 7}}, {"pos": {"y": 18, "x": 8}}, {"pos": {"y": 16, "x": 9}}, {"pos": {"y": 17, "x": 9}}], "timer": 0}}, "marsballs": [], "spawnPoints": {"blue": [], "red": []}}