{"info": {"gameMode": "normal", "name": "Portugal. The Map", "author": "Beast  Mode"}, "portals": {"30,12": {}, "34,28": {"cooldown": 0, "destination": {"y": 20, "x": 30}}, "34,27": {"cooldown": 0, "destination": {"y": 20, "x": 30}}, "30,20": {}, "26,4": {"cooldown": 0, "destination": {"y": 12, "x": 30}}, "26,5": {"cooldown": 0, "destination": {"y": 12, "x": 30}}}, "fields": {"10,23": {"defaultState": "red"}, "9,22": {"defaultState": "red"}, "59,29": {"defaultState": "off"}, "58,28": {"defaultState": "off"}, "3,4": {"defaultState": "off"}, "53,12": {"defaultState": "red"}, "1,4": {"defaultState": "off"}, "58,29": {"defaultState": "off"}, "6,19": {"defaultState": "blue"}, "1,3": {"defaultState": "off"}, "3,3": {"defaultState": "off"}, "54,13": {"defaultState": "red"}, "50,9": {"defaultState": "blue"}, "57,29": {"defaultState": "off"}, "57,28": {"defaultState": "off"}, "2,4": {"defaultState": "off"}, "7,20": {"defaultState": "blue"}, "51,10": {"defaultState": "blue"}, "2,3": {"defaultState": "off"}, "59,28": {"defaultState": "off"}}, "switches": {"50,13": {"toggle": [{"pos": {"y": 13, "x": 54}}, {"pos": {"y": 12, "x": 53}}, {"pos": {"y": 10, "x": 51}}, {"pos": {"y": 9, "x": 50}}], "timer": 0}, "48,28": {"toggle": [{"pos": {"y": 29, "x": 59}}, {"pos": {"y": 28, "x": 59}}, {"pos": {"y": 29, "x": 58}}, {"pos": {"y": 28, "x": 58}}, {"pos": {"y": 29, "x": 57}}, {"pos": {"y": 28, "x": 57}}], "timer": 0}, "12,4": {"toggle": [{"pos": {"y": 3, "x": 1}}, {"pos": {"y": 4, "x": 1}}, {"pos": {"y": 3, "x": 2}}, {"pos": {"y": 4, "x": 2}}, {"pos": {"y": 3, "x": 3}}, {"pos": {"y": 4, "x": 3}}], "timer": 0}, "10,19": {"toggle": [{"pos": {"y": 19, "x": 6}}, {"pos": {"y": 20, "x": 7}}, {"pos": {"y": 22, "x": 9}}, {"pos": {"y": 23, "x": 10}}], "timer": 0}}, "marsballs": [], "spawnPoints": {"blue": [], "red": []}}