{"info": {"gameMode": "normal", "name": "Untitled", "author": "Anonymous"}, "portals": {"50,10": {"cooldown": 0, "destination": {"y": 7, "x": 56}}, "12,19": {}, "18,31": {}, "62,19": {}, "56,7": {}, "24,28": {"cooldown": 0, "destination": {"y": 31, "x": 18}}}, "fields": {"13,19": {"defaultState": "blue"}, "12,20": {"defaultState": "blue"}, "27,19": {"defaultState": "red"}, "62,18": {"defaultState": "red"}, "28,20": {"defaultState": "red"}, "61,19": {"defaultState": "red"}, "46,18": {"defaultState": "blue"}, "47,19": {"defaultState": "blue"}}, "switches": {"33,8": {"toggle": [], "timer": 0}, "41,30": {"toggle": [], "timer": 0}}, "marsballs": [], "spawnPoints": {"blue": [], "red": []}}