{"info": {"gameMode": "normal", "name": "Buster", "author": "Bamboozler"}, "portals": {"4,1": {"cooldown": 5, "destination": {"y": 14, "x": 2}}, "42,20": {}, "2,14": {}, "40,33": {"cooldown": 5, "destination": {"y": 20, "x": 42}}}, "fields": {"12,11": {"defaultState": "off"}, "12,10": {"defaultState": "off"}, "12,12": {"defaultState": "off"}, "12,17": {"defaultState": "off"}, "12,16": {"defaultState": "off"}, "12,19": {"defaultState": "off"}, "12,18": {"defaultState": "off"}, "32,24": {"defaultState": "off"}, "32,25": {"defaultState": "off"}, "12,9": {"defaultState": "off"}, "32,16": {"defaultState": "off"}, "32,15": {"defaultState": "off"}, "32,23": {"defaultState": "off"}, "32,22": {"defaultState": "off"}, "32,17": {"defaultState": "off"}, "32,18": {"defaultState": "off"}}, "switches": {"10,14": {"toggle": [{"pos": {"y": 9, "x": 12}}, {"pos": {"y": 10, "x": 12}}, {"pos": {"y": 11, "x": 12}}, {"pos": {"y": 12, "x": 12}}, {"pos": {"y": 16, "x": 12}}, {"pos": {"y": 17, "x": 12}}, {"pos": {"y": 18, "x": 12}}, {"pos": {"y": 19, "x": 12}}], "timer": 0}, "34,20": {"toggle": [{"pos": {"y": 15, "x": 32}}, {"pos": {"y": 16, "x": 32}}, {"pos": {"y": 17, "x": 32}}, {"pos": {"y": 18, "x": 32}}, {"pos": {"y": 22, "x": 32}}, {"pos": {"y": 23, "x": 32}}, {"pos": {"y": 24, "x": 32}}, {"pos": {"y": 25, "x": 32}}], "timer": 0}}, "marsballs": [], "spawnPoints": {"blue": [], "red": [{"y": 8, "x": 8, "radius": 4, "weight": 1}]}}