{"info": {"name": "Pacman v1.3", "author": "First"}, "switches": {"52,20": {"toggle": [{"pos": {"y": 18, "x": 51}}, {"pos": {"y": 19, "x": 51}}, {"pos": {"y": 20, "x": 51}}]}, "23,55": {"toggle": []}, "33,5": {"toggle": []}, "34,55": {"toggle": []}, "35,55": {"toggle": []}, "6,19": {"toggle": [{"pos": {"y": 18, "x": 7}}, {"pos": {"y": 19, "x": 7}}, {"pos": {"y": 20, "x": 7}}]}, "6,18": {"toggle": [{"pos": {"y": 18, "x": 7}}, {"pos": {"y": 19, "x": 7}}, {"pos": {"y": 20, "x": 7}}]}, "24,5": {"toggle": []}, "34,5": {"toggle": []}, "24,55": {"toggle": []}, "52,18": {"toggle": [{"pos": {"y": 18, "x": 51}}, {"pos": {"y": 19, "x": 51}}, {"pos": {"y": 20, "x": 51}}]}, "25,55": {"toggle": []}, "52,19": {"toggle": [{"pos": {"y": 18, "x": 51}}, {"pos": {"y": 19, "x": 51}}, {"pos": {"y": 20, "x": 51}}]}, "35,5": {"toggle": []}, "23,5": {"toggle": []}, "33,55": {"toggle": []}, "6,20": {"toggle": [{"pos": {"y": 18, "x": 7}}, {"pos": {"y": 19, "x": 7}}, {"pos": {"y": 20, "x": 7}}]}, "25,5": {"toggle": []}}, "portals": {"29,35": {"destination": {"y": 35, "x": 29}}, "2,31": {"destination": {"y": 31, "x": 2}}, "2,30": {"destination": {"y": 30, "x": 2}}, "2,29": {"destination": {"y": 29, "x": 2}}, "56,31": {"destination": {"y": 31, "x": 56}}, "56,30": {"destination": {"y": 30, "x": 56}}, "56,29": {"destination": {"y": 29, "x": 56}}, "4,36": {"destination": {"y": 36, "x": 4}}}, "fields": {"29,27": {"defaultState": "blue"}, "33,6": {"defaultState": "on"}, "35,6": {"defaultState": "on"}, "7,20": {"defaultState": "on"}, "33,54": {"defaultState": "on"}, "30,27": {"defaultState": "blue"}, "2,18": {"defaultState": "red"}, "56,42": {"defaultState": "red"}, "56,43": {"defaultState": "red"}, "2,17": {"defaultState": "red"}, "24,54": {"defaultState": "on"}, "29,54": {"defaultState": "blue"}, "51,20": {"defaultState": "on"}, "29,58": {"defaultState": "red"}, "28,6": {"defaultState": "blue"}, "7,18": {"defaultState": "on"}, "7,19": {"defaultState": "on"}, "28,2": {"defaultState": "red"}, "23,54": {"defaultState": "on"}, "56,18": {"defaultState": "red"}, "29,6": {"defaultState": "blue"}, "29,2": {"defaultState": "red"}, "35,54": {"defaultState": "on"}, "25,54": {"defaultState": "on"}, "30,54": {"defaultState": "blue"}, "24,6": {"defaultState": "on"}, "30,58": {"defaultState": "red"}, "56,17": {"defaultState": "red"}, "28,27": {"defaultState": "blue"}, "34,6": {"defaultState": "on"}, "51,18": {"defaultState": "on"}, "51,19": {"defaultState": "on"}, "34,54": {"defaultState": "on"}, "2,42": {"defaultState": "red"}, "2,43": {"defaultState": "red"}, "23,6": {"defaultState": "on"}, "25,6": {"defaultState": "on"}}}