{"info": {"gameMode": "normal", "name": "Falcon", "author": "Tumblewood"}, "portals": {"10,23": {"cooldown": 0, "destination": {"y": 17, "x": 18}}, "9,23": {"cooldown": 0, "destination": {"y": 17, "x": 18}}, "10,19": {"cooldown": 0, "destination": {"y": 25, "x": 18}}, "35,21": {"cooldown": 500, "destination": {"y": 21, "x": 26}}, "18,25": {}, "18,17": {}, "9,19": {"cooldown": 0, "destination": {"y": 25, "x": 18}}, "26,21": {"cooldown": 500, "destination": {"y": 21, "x": 35}}}, "fields": {"20,14": {"defaultState": "blue"}, "20,29": {"defaultState": "red"}, "9,24": {"defaultState": "blue"}, "10,24": {"defaultState": "blue"}, "10,18": {"defaultState": "red"}, "20,27": {"defaultState": "red"}, "20,26": {"defaultState": "red"}, "9,18": {"defaultState": "red"}, "20,15": {"defaultState": "blue"}, "20,16": {"defaultState": "blue"}, "23,21": {"defaultState": "off"}, "20,13": {"defaultState": "blue"}, "20,28": {"defaultState": "red"}}, "switches": {"22,17": {"toggle": [{"pos": {"y": 16, "x": 20}}, {"pos": {"y": 15, "x": 20}}, {"pos": {"y": 14, "x": 20}}, {"pos": {"y": 13, "x": 20}}, {"pos": {"y": 21, "x": 23}}], "timer": 0}, "38,13": {"toggle": [{"pos": {"y": 15, "x": 38}}], "timer": 0}, "22,25": {"toggle": [{"pos": {"y": 26, "x": 20}}, {"pos": {"y": 27, "x": 20}}, {"pos": {"y": 28, "x": 20}}, {"pos": {"y": 29, "x": 20}}, {"pos": {"y": 21, "x": 23}}], "timer": 0}, "38,29": {"toggle": [{"pos": {"y": 27, "x": 38}}], "timer": 0}}, "marsballs": [], "spawnPoints": {"blue": [{"y": 14, "x": 13, "radius": 4, "weight": 1}], "red": [{"y": 28, "x": 13, "radius": 4, "weight": 1}]}}