{"info": {"gameMode": "normal", "name": "Hydro", "author": "Sadness"}, "portals": {}, "fields": {"8,16": {"defaultState": "off"}, "34,34": {"defaultState": "off"}, "32,24": {"defaultState": "off"}, "24,32": {"defaultState": "off"}, "16,8": {"defaultState": "off"}, "6,6": {"defaultState": "off"}}, "switches": {"25,31": {"toggle": [{"pos": {"y": 32, "x": 24}}], "timer": 0}, "15,9": {"toggle": [{"pos": {"y": 8, "x": 16}}], "timer": 0}, "32,32": {"toggle": [{"pos": {"y": 6, "x": 6}}], "timer": 0}, "8,8": {"toggle": [{"pos": {"y": 34, "x": 34}}], "timer": 0}, "31,25": {"toggle": [{"pos": {"y": 24, "x": 32}}], "timer": 0}, "9,15": {"toggle": [{"pos": {"y": 16, "x": 8}}], "timer": 0}}, "marsballs": [], "spawnPoints": {"blue": [], "red": []}}