{"info": {"gameMode": "normal", "name": "Flemington 3", "author": "Equ1"}, "portals": {"22,21": {"cooldown": 0, "destination": {"y": 29, "x": 30}}, "20,29": {}, "29,20": {"cooldown": 0, "destination": {"y": 29, "x": 20}}, "28,21": {"cooldown": 0, "destination": {"y": 29, "x": 20}}, "30,29": {}, "21,20": {"cooldown": 0, "destination": {"y": 29, "x": 30}}}, "fields": {"22,22": {"defaultState": "blue"}, "22,14": {"defaultState": "red"}, "29,21": {"defaultState": "red"}, "30,12": {"defaultState": "blue"}, "20,12": {"defaultState": "red"}, "28,22": {"defaultState": "red"}, "28,14": {"defaultState": "blue"}, "21,21": {"defaultState": "blue"}}, "switches": {"19,15": {"toggle": [{"pos": {"y": 12, "x": 20}}, {"pos": {"y": 14, "x": 22}}], "timer": 0}, "31,15": {"toggle": [{"pos": {"y": 12, "x": 30}}, {"pos": {"y": 14, "x": 28}}], "timer": 0}}, "marsballs": [], "spawnPoints": {"blue": [{"y": 26, "x": 32, "radius": 3, "weight": 1}], "red": [{"y": 26, "x": 18, "radius": 3, "weight": 1}]}}