{"info": {"gameMode": "normal", "name": "Whirr", "author": "Thanos Ball"}, "portals": {}, "fields": {"16,24": {"defaultState": "off"}, "16,25": {"defaultState": "off"}, "35,20": {"defaultState": "off"}, "36,17": {"defaultState": "off"}, "17,22": {"defaultState": "off"}, "35,18": {"defaultState": "off"}, "17,23": {"defaultState": "off"}, "15,24": {"defaultState": "off"}, "36,19": {"defaultState": "off"}, "16,23": {"defaultState": "off"}, "34,19": {"defaultState": "off"}, "37,18": {"defaultState": "off"}, "35,19": {"defaultState": "off"}, "36,18": {"defaultState": "off"}, "18,23": {"defaultState": "off"}, "17,24": {"defaultState": "off"}}, "switches": {"37,14": {"toggle": [{"pos": {"y": 18, "x": 37}}, {"pos": {"y": 19, "x": 36}}, {"pos": {"y": 18, "x": 36}}, {"pos": {"y": 17, "x": 36}}, {"pos": {"y": 20, "x": 35}}, {"pos": {"y": 19, "x": 35}}, {"pos": {"y": 18, "x": 35}}, {"pos": {"y": 19, "x": 34}}], "timer": 0}, "15,28": {"toggle": [{"pos": {"y": 24, "x": 15}}, {"pos": {"y": 23, "x": 16}}, {"pos": {"y": 24, "x": 16}}, {"pos": {"y": 25, "x": 16}}, {"pos": {"y": 22, "x": 17}}, {"pos": {"y": 23, "x": 17}}, {"pos": {"y": 24, "x": 17}}, {"pos": {"y": 23, "x": 18}}], "timer": 0}}, "marsballs": [], "spawnPoints": {"blue": [], "red": []}}